openscan/__init__.py
openscan/scanner.py
openscan-0.1.0.dist-info/licenses/LICENSE
openscan-0.1.0.dist-info/METADATA
openscan-0.1.0.dist-info/WHEEL
openscan-0.1.0.dist-info/top_level.txt
openscan-0.1.0.dist-info/RECORD
